{
  "recipes": [
    {
      "id": "1",
      "title": "우유달걀카레",
      "ingredients": [
        "카레가루 3.5큰술",
        "달걀 1개",
        "우유 200ml",
        "양파 1/2개",
        "통조림 햄 작은거"
      ],
      "method": "1. 먼저 양파 1/2개 먹기좋은 크기로 잘라주시구요. 햄도 한입 크기로 깍뚝 썰어주시구요.. 2.뜨겁게 달궈진 냄비에 식용유를 붓구요.양파와 햄을 볶아주세요. 4. 양파와 햄이 노릇노릇하게 볶아졌으면 우유 200ml 부어주시구요.5.카레가 걸쭉해져서 끓어오르면 계란 1개를 넣고 풀어주세요.",
      "cookingTime": "15분"
    },
    {
      "id": "2",
      "title": "고구마 두유 라떼",
      "ingredients": [
        "고구마 1개",
        "두유파우치 1개",
        "꿀 1/2큰술",
        "시나몬가루 약간"
      ],
      "method": "1.먼저 고구마를 깨끗이 씻어서 필러로 껍질을 깨끗이 벗기고 1cm 두께로 썰어서 전자렌지 전용 용기에 담아 줍니다. 2. 전자렌지에서 고구마 5분 돌리기. 3. 믹서기에 고구마를 잘 갈아주고 두유파우치를 넣어줍니다. 4. 꿀과 시나몬을 넣어서 완성하기. ",
      "cookingTime": "10분"
    },
    {
      "id": "3",
      "title": "마약 토스트",
      "ingredients": [
        "식빵 1개",
        "계란 1개",
        "마요네즈 소량",
        "설탕 3꼬집"
      ],
      "method": "1. 식빵 1개를 준비. 2. 마요네즈를 식빵 테두리를 타고 한 바퀴 둘러 주세요. 3. 설탕 3꼬집을 마요네즈 안쪽 식빵에 고루 고루 뿌려주세요. 4. 계란을 깨서 마요네즈 테두리에 담아 주세요. 5. 전자렌지에 넣고 반숙을 원하시면 1분, 완숙을 원하시면 2분을 돌려 주시면 돼요. ",
      "cookingTime": "5분"
    },
    {
      "id": "dc4e",
      "title": "오이시쿠나레 오무라이스",
      "ingredients": [
        "계란",
        "밥",
        "야채",
        "케챱"
      ],
      "method": "1. 오무라이스를 만든다. 2. 귀여운 소녀들과 오이시쿠나레 오이시쿠나레 모에모에큥을 외친다. 3. 케챱을 하트모양으로 뿌린다",
      "cookingTime": "500분"
    },
    {
      "id": "7ffb",
      "title": "일본 계란 카레",
      "ingredients": [
        "일본 카레 블럭",
        "밥",
        "계란",
        "양파",
        "감자",
        "우유"
      ],
      "method": "1. 잘 만들면 된다",
      "cookingTime": "5분"
    },
    {
      "id": "0fa7",
      "title": "청국장",
      "ingredients": [
        "청국장"
      ],
      "method": "긋",
      "cookingTime": "900분"
    }
  ]
}